topsis/__init__.py
topsis/topsis.py
Topsis_Krish_102203848-1.0.2.dist-info/LICENSE
Topsis_Krish_102203848-1.0.2.dist-info/METADATA
Topsis_Krish_102203848-1.0.2.dist-info/WHEEL
Topsis_Krish_102203848-1.0.2.dist-info/entry_points.txt
Topsis_Krish_102203848-1.0.2.dist-info/top_level.txt
Topsis_Krish_102203848-1.0.2.dist-info/RECORD
