Metadata-Version: 2.2
Name: Topsis_Krish_102203848
Version: 1.0.2
Summary: A Python package to implement TOPSIS (Technique for Order of Preference by Similarity to Ideal Solution)
Home-page: https://github.com/Krish2728/Topsis_Krish_102203848
Author: Krish
Author-email: krishkumaar2703@gmail.com
Classifier: Programming Language :: Python :: 3
Classifier: License :: OSI Approved :: MIT License
Classifier: Operating System :: OS Independent
Requires-Python: >=3.6
License-File: LICENSE
Requires-Dist: numpy
Requires-Dist: pandas
Dynamic: author
Dynamic: author-email
Dynamic: classifier
Dynamic: description
Dynamic: description-content-type
Dynamic: home-page
Dynamic: requires-dist
Dynamic: requires-python
Dynamic: summary
